{
  "date": "7/21",
  "previewData": [
    "1969年7月21日 “阿波罗”登上月球",
    "710年7月21日 李隆基政变诛韦后",
    "-776年7月21日 世界上第一次奥林匹克运动会在古希腊举行",
    "710年7月21日 唐代著名才女上官婉儿逝世",
    "2012年7月21日 北京特大暴雨",
    "1998年7月21日 武汉遭受百年罕见大暴雨袭击"
  ],
  "mainData": [
    {
      "d": "-776年7月21日",
      "t": "世界上第一次奥林匹克运动会在古希腊举行"
    },
    {
      "d": "-356年7月21日",
      "t": "亚底米神庙因遭人蓄意纵火而被毁"
    },
    {
      "d": "541年7月21日",
      "t": "隋文帝杨坚诞辰"
    },
    {
      "d": "710年7月21日",
      "t": "李隆基政变诛韦后"
    },
    {
      "d": "710年7月21日",
      "t": "唐代著名才女上官婉儿逝世"
    },
    {
      "d": "1298年7月21日",
      "t": "苏格兰独立战争中的法兰克林战役爆发"
    },
    {
      "d": "1568年7月21日",
      "t": "尼德兰独立战争中的杰明根战役爆发"
    },
    {
      "d": "1588年7月21日",
      "t": "英国击溃西班牙无敌舰队"
    },
    {
      "d": "1654年7月21日",
      "t": "甘肃天水发生8级地震"
    },
    {
      "d": "1796年7月21日",
      "t": "苏格兰诗人罗伯特·彭斯逝世"
    },
    {
      "d": "1816年7月21日",
      "t": "路透社创办人路透出生"
    },
    {
      "d": "1842年7月21日",
      "t": "镇江抗敌"
    },
    {
      "d": "1861年7月21日",
      "t": "美国南北战争 布尔伦河战役爆发"
    },
    {
      "d": "1894年7月21日",
      "t": "资产阶级改良主义思想家薛福成病逝"
    },
    {
      "d": "1899年7月21日",
      "t": "海明威诞生"
    },
    {
      "d": "1906年7月21日",
      "t": "台湾音乐家邓雨贤出生"
    },
    {
      "d": "1919年7月21日",
      "t": "《天津学生联合会会报》创刊"
    },
    {
      "d": "1921年7月21日",
      "t": "米切尔证实从空中投弹可击沉军舰"
    },
    {
      "d": "1928年7月21日",
      "t": "戏剧皇后埃伦·特里逝世"
    },
    {
      "d": "1928年7月21日",
      "t": "全国反日大会在上海召开"
    },
    {
      "d": "1944年7月21日",
      "t": "豫鄂农民起义并歼国民党军第二十八师"
    },
    {
      "d": "1944年7月21日",
      "t": "美军登陆日本关岛"
    },
    {
      "d": "1944年7月21日",
      "t": "波兰国家复兴节"
    },
    {
      "d": "1946年7月21日",
      "t": "关向应病逝"
    },
    {
      "d": "1950年7月21日",
      "t": "中共中央转发北京市委关于整风工作的报告"
    },
    {
      "d": "1954年7月21日",
      "t": "关于印度支那问题的日内瓦协议签订"
    },
    {
      "d": "1960年7月21日",
      "t": "英国人创造单身横渡大西洋新纪录"
    },
    {
      "d": "1960年7月21日",
      "t": "西丽玛沃·班达拉奈克成为斯里兰卡第一位女总理"
    },
    {
      "d": "1963年7月21日",
      "t": "琼瑶发表第一部长篇小说《窗外》"
    },
    {
      "d": "1968年7月21日",
      "t": "721工人上大学"
    },
    {
      "d": "1969年7月21日",
      "t": "“阿波罗”登上月球"
    },
    {
      "d": "1970年7月21日",
      "t": "埃及阿斯旺水坝竣工"
    },
    {
      "d": "1977年7月21日",
      "t": "利比亚埃及四天战争爆发"
    },
    {
      "d": "1983年7月21日",
      "t": "波兰政府解除军事管制法"
    },
    {
      "d": "1985年7月21日",
      "t": "潜水员找到几百万美元的珍宝"
    },
    {
      "d": "1986年7月21日",
      "t": "中国近代天文学的主要奠基人张钰哲逝世"
    },
    {
      "d": "1988年7月21日",
      "t": "中国机电产品进出口商会成立"
    },
    {
      "d": "1990年7月21日",
      "t": "我国与沙特建交"
    },
    {
      "d": "1990年7月21日",
      "t": "北京正负电子对撞机正式通过验收"
    },
    {
      "d": "1990年7月21日",
      "t": "中国计算机专家慈云桂逝世"
    },
    {
      "d": "1995年7月21日",
      "t": "我国北方第一条跨海铁路通车"
    },
    {
      "d": "1995年7月21日",
      "t": "第五次台海危机"
    },
    {
      "d": "1998年7月21日",
      "t": "桑兰在纽约友好运动会上意外受伤"
    },
    {
      "d": "1998年7月21日",
      "t": "军队武警不再经商"
    },
    {
      "d": "1998年7月21日",
      "t": "武汉遭受百年罕见大暴雨袭击"
    },
    {
      "d": "2002年7月21日",
      "t": "我国与瑙鲁建交"
    },
    {
      "d": "2003年7月21日",
      "t": "城市流浪乞讨者救助管理办法实施细则"
    },
    {
      "d": "2006年7月21日",
      "t": "赤柬军方高层塔莫逝世"
    },
    {
      "d": "2007年7月21日",
      "t": "印度诞生首位女总统普拉蒂巴·帕蒂尔"
    },
    {
      "d": "2008年7月21日",
      "t": "尼泊尔制宪会议选举第一任总统拉姆·亚达夫"
    },
    {
      "d": "2011年7月21日",
      "t": "中国光学之父王大珩逝世"
    },
    {
      "d": "2012年7月21日",
      "t": "北京特大暴雨"
    },
    {
      "d": "2012年7月21日",
      "t": "中国科学院院士徐世浙逝世"
    }
  ]
}