{
  "date": "1/11",
  "previewData": [
    "1982年1月11日 邓小平首次提出“一个国家，两种制度”的概念",
    "1851年1月11日 太平天国金田起义",
    "1868年1月11日 蔡元培诞辰",
    "1957年1月11日 毛泽东为刘胡兰烈士亲笔题词“生的伟大，死的光荣”",
    "1938年1月11日 《新华日报》创刊",
    "1926年1月11日 张作霖宣布东三省独立"
  ],
  "mainData": [
    {
      "d": "532年1月11日",
      "t": "东罗马帝国的都城君士坦丁堡爆发尼卡起义"
    },
    {
      "d": "705年1月11日",
      "t": "教皇约翰六世逝世"
    },
    {
      "d": "1295年1月11日",
      "t": "元朝初期政治家伯颜去世"
    },
    {
      "d": "1569年1月11日",
      "t": "英格兰首次发行彩票"
    },
    {
      "d": "1571年1月11日",
      "t": "奥地利贵族开始享有宗教自由"
    },
    {
      "d": "1757年1月11日",
      "t": "美国经济学家汉密尔顿诞辰"
    },
    {
      "d": "1787年1月11日",
      "t": "天王星的两颗卫星被发现"
    },
    {
      "d": "1800年1月11日",
      "t": "直流发电机之父耶德利克·阿纽什出生"
    },
    {
      "d": "1851年1月11日",
      "t": "太平天国金田起义"
    },
    {
      "d": "1868年1月11日",
      "t": "蔡元培诞辰"
    },
    {
      "d": "1879年1月11日",
      "t": "英国祖鲁战争爆发"
    },
    {
      "d": "1885年1月11日",
      "t": "中日友好先驱者之一内山完造诞辰"
    },
    {
      "d": "1885年1月11日",
      "t": "美国女权运动领袖爱莉丝·保罗出生"
    },
    {
      "d": "1903年1月11日",
      "t": "伟大的国际主义战士罗生特诞辰"
    },
    {
      "d": "1914年1月11日",
      "t": "本世纪初女权运动迅速发展"
    },
    {
      "d": "1917年1月11日",
      "t": "中国抚顺煤矿瓦斯爆炸，900余名矿工死亡"
    },
    {
      "d": "1919年1月11日",
      "t": "苏俄人民委员会颁布余粮收集制法令"
    },
    {
      "d": "1919年1月11日",
      "t": "罗马尼亚并吞特兰西瓦尼亚"
    },
    {
      "d": "1922年1月11日",
      "t": "加拿大医生班廷博士首次使用胰岛素治疗糖尿病"
    },
    {
      "d": "1925年1月11日",
      "t": "中国共产党第四次全国代表大会在上海召开"
    },
    {
      "d": "1926年1月11日",
      "t": "张作霖宣布东三省独立"
    },
    {
      "d": "1928年1月11日",
      "t": "英国小说家托马斯·哈代去世"
    },
    {
      "d": "1930年1月11日",
      "t": "海尔·塞拉西成为埃塞俄比亚新皇帝"
    },
    {
      "d": "1938年1月11日",
      "t": "《新华日报》创刊"
    },
    {
      "d": "1942年1月11日",
      "t": "日军开始占领荷属东印度"
    },
    {
      "d": "1943年1月11日",
      "t": "中英中美签订新约废除在华治外法权"
    },
    {
      "d": "1944年1月11日",
      "t": "罗斯福召开太平洋作战会议"
    },
    {
      "d": "1946年1月11日",
      "t": "阿尔巴尼亚人民共和国成立"
    },
    {
      "d": "1947年1月11日",
      "t": "中央军委指示东北部队大量歼敌"
    },
    {
      "d": "1957年1月11日",
      "t": "英国向也门南部发动侵略战争"
    },
    {
      "d": "1957年1月11日",
      "t": "毛泽东为刘胡兰烈士亲笔题词“生的伟大，死的光荣”"
    },
    {
      "d": "1958年1月11日",
      "t": "中共中央“南宁会议”召开"
    },
    {
      "d": "1962年1月11日",
      "t": "中共召开“七千人大会”，纠正“大跃进”的错误"
    },
    {
      "d": "1962年1月11日",
      "t": "肯尼迪鼓吹进一步扩军"
    },
    {
      "d": "1966年1月11日",
      "t": "英迪拉·甘地出任印度总理"
    },
    {
      "d": "1974年1月11日",
      "t": "南越宣布对西沙群岛、南沙群岛拥有主权"
    },
    {
      "d": "1979年1月11日",
      "t": "给“四类分子”摘掉帽子"
    },
    {
      "d": "1982年1月11日",
      "t": "邓小平首次提出“一个国家，两种制度”的概念"
    },
    {
      "d": "1983年1月11日",
      "t": "赵紫阳总理访问坦桑尼亚"
    },
    {
      "d": "1989年1月11日",
      "t": "斯里兰卡取消长达五年的紧急状态"
    },
    {
      "d": "1991年1月11日",
      "t": "首次墨西哥――中美洲首脑会议闭幕"
    },
    {
      "d": "1999年1月11日",
      "t": "接受活性人体细胞和牛胶原蛋白合成皮肤移植的第一例病人"
    },
    {
      "d": "2002年1月11日",
      "t": "世界地铁无裤日"
    },
    {
      "d": "2008年1月11日",
      "t": "首先登上珠穆朗玛峰的埃德蒙·希拉里爵士去世，享年88岁"
    },
    {
      "d": "2011年1月11日",
      "t": "中国歼20隐形战机首飞成功"
    },
    {
      "d": "2014年1月11日",
      "t": "以色列总理沙龙病逝"
    },
    {
      "d": "2019年1月11日",
      "t": "英国著名数学家迈克尔·阿蒂亚去世"
    }
  ]
}