{
  "date": "9/23",
  "previewData": [
    "1993年9月23日 北京申办2000年奥运会失败",
    "1215年9月23日 元世祖忽必烈出生",
    "1969年9月23日 中国成功地进行了首次地下核试验",
    "1831年9月23日 法拉第发明发电机",
    "1993年9月23日 邓小平关于香港问题的谈话发表",
    "617年9月23日 李渊起兵反隋"
  ],
  "mainData": [
    {
      "d": "-63年9月23日",
      "t": "罗马帝国的开国君主屋大维出生"
    },
    {
      "d": "617年9月23日",
      "t": "李渊起兵反隋"
    },
    {
      "d": "1122年9月23日",
      "t": "沃尔姆斯宗教协定缔结"
    },
    {
      "d": "1215年9月23日",
      "t": "元世祖忽必烈出生"
    },
    {
      "d": "1803年9月23日",
      "t": "阿萨耶战役爆发"
    },
    {
      "d": "1831年9月23日",
      "t": "法拉第发明发电机"
    },
    {
      "d": "1846年9月23日",
      "t": "伽勒第一次观察到海王星"
    },
    {
      "d": "1850年9月23日",
      "t": "乌拉圭民族英雄阿蒂加斯逝世"
    },
    {
      "d": "1862年9月23日",
      "t": "俾斯麦出任普鲁士首相，德国开始统一"
    },
    {
      "d": "1870年9月23日",
      "t": "法国大作家梅里美去世"
    },
    {
      "d": "1877年9月23日",
      "t": "法国数学家、天文学家勒维耶去世"
    },
    {
      "d": "1889年9月23日",
      "t": "日本游戏巨头任天堂创立"
    },
    {
      "d": "1897年9月23日",
      "t": "比利时画家保罗·德尔沃出生"
    },
    {
      "d": "1900年9月23日",
      "t": "第二国际巴黎代表大会召开"
    },
    {
      "d": "1902年9月23日",
      "t": "中国杰出的数学家苏步青出生"
    },
    {
      "d": "1905年9月23日",
      "t": "徐锡麟等创办大通学堂"
    },
    {
      "d": "1913年9月23日",
      "t": "人类第一次飞越地中海"
    },
    {
      "d": "1923年9月23日",
      "t": "德国消极抵抗赔款政策停止执行"
    },
    {
      "d": "1926年9月23日",
      "t": "美国色士风手约翰·柯川出生"
    },
    {
      "d": "1930年9月23日",
      "t": "北平国民政府迁都太原"
    },
    {
      "d": "1939年9月23日",
      "t": "精神分析学奠基人弗洛伊德逝世"
    },
    {
      "d": "1940年9月23日",
      "t": "补选胡适为中央研究院院长事风波大起"
    },
    {
      "d": "1943年9月23日",
      "t": "法西斯傀儡政权意大利社会共和国成立"
    },
    {
      "d": "1946年9月23日",
      "t": "我军开始使用“人民解放军”称号"
    },
    {
      "d": "1946年9月23日",
      "t": "香港电影导演吴宇森出生"
    },
    {
      "d": "1949年9月23日",
      "t": "苏联研制成功原子弹"
    },
    {
      "d": "1953年9月23日",
      "t": "中国文学艺术界联合会成立"
    },
    {
      "d": "1969年9月23日",
      "t": "中国成功地进行了首次地下核试验"
    },
    {
      "d": "1970年9月23日",
      "t": "“山药蛋派”鼻祖赵树理逝世"
    },
    {
      "d": "1973年9月23日",
      "t": "智利著名诗人聂鲁达逝世"
    },
    {
      "d": "1973年9月23日",
      "t": "胡安·庇隆再次当选阿根廷总统"
    },
    {
      "d": "1983年9月23日",
      "t": "北京图书馆新馆奠基仪式举行"
    },
    {
      "d": "1985年9月23日",
      "t": "网红“凤姐”出生"
    },
    {
      "d": "1987年9月23日",
      "t": "国际贸易中商品命名和编码系统开始统一"
    },
    {
      "d": "1991年9月23日",
      "t": "“中国船王”包玉刚先生逝世"
    },
    {
      "d": "1992年9月23日",
      "t": "钱其琛在联大阐述联合国改革方向"
    },
    {
      "d": "1993年9月23日",
      "t": "莫斯科发生流血事件　叶利钦解除议会警卫武装"
    },
    {
      "d": "1993年9月23日",
      "t": "邓小平关于香港问题的谈话发表"
    },
    {
      "d": "1993年9月23日",
      "t": "北京申办2000年奥运会失败"
    },
    {
      "d": "1994年9月23日",
      "t": "1994年体坛45英杰评选揭晓"
    },
    {
      "d": "1996年9月23日",
      "t": "谭盾获加拿大“格兰-郭德”国际音乐大奖"
    },
    {
      "d": "1997年9月23日",
      "t": "美日正式公布新防卫合作方针"
    },
    {
      "d": "1997年9月23日",
      "t": "超级并行计算机“深蓝”告别棋坛"
    },
    {
      "d": "1997年9月23日",
      "t": "沈阳铁路局试行火车"
    },
    {
      "d": "1998年9月23日",
      "t": "安理会通过科索沃问题决议  中国投弃权票"
    },
    {
      "d": "1999年9月23日",
      "t": "朝鲜前国家领导人李钟玉逝世"
    },
    {
      "d": "2011年9月23日",
      "t": "中国首台黄金ATM机北京亮相"
    },
    {
      "d": "2015年9月23日",
      "t": "中科院发现“超级材料”的石墨烯新结构和新奇应用"
    },
    {
      "d": "2015年9月23日",
      "t": "叶良辰走红"
    },
    {
      "d": "2018年9月23日",
      "t": "“光纤之父”、中科院外籍院士高锟逝世"
    },
    {
      "d": "2019年9月23日",
      "t": "全球阻击电子烟"
    }
  ]
}